[{"supplier":1,"late_cnt":1768},{"supplier":7,"late_cnt":1538},{"supplier":2,"late_cnt":918},{"supplier":4,"late_cnt":494},{"supplier":3,"late_cnt":483},{"supplier":18,"late_cnt":384},{"supplier":39,"late_cnt":362},{"supplier":11,"late_cnt":329},{"supplier":10,"late_cnt":287},{"supplier":25,"late_cnt":280},{"supplier":104,"late_cnt":263},{"supplier":81,"late_cnt":240},{"supplier":117,"late_cnt":234},{"supplier":2720,"late_cnt":224},{"supplier":8,"late_cnt":221},{"supplier":6,"late_cnt":209},{"supplier":41,"late_cnt":203},{"supplier":96,"late_cnt":203},{"supplier":79,"late_cnt":186},{"supplier":15,"late_cnt":184},{"supplier":100,"late_cnt":178},{"supplier":28,"late_cnt":171},{"supplier":60,"late_cnt":169},{"supplier":12,"late_cnt":169},{"supplier":22,"late_cnt":167}]